setup.py
bRusky/__init__.py
bRusky/commands.py
bRusky/exceptions.py
bRusky/sendCALLS.py
bRusky/sendSMS.py
bRusky.egg-info/PKG-INFO
bRusky.egg-info/SOURCES.txt
bRusky.egg-info/dependency_links.txt
bRusky.egg-info/entry_points.txt
bRusky.egg-info/requires.txt
bRusky.egg-info/top_level.txt