Metadata-Version: 1.0
Name: bRusky
Version: 0.4
Summary: Author - t.me/extreames
Home-page: UNKNOWN
Author: eXtreames
Author-email: UNKNOWN
License: MPL-2.0
Platform: UNKNOWN
